mlxp/__init__.py
mlxp/enumerations.py
mlxp/errors.py
mlxp/launcher.py
mlxp/logger.py
mlxp/mlxpsub.py
mlxp/parser.py
mlxp/reader.py
mlxp/scheduler.py
mlxp/version_manager.py
mlxp/_internal/__init__.py
mlxp/_internal/_interactive_mode.py
mlxp/_internal/configure.py
mlxp/data_structures/__init__.py
mlxp/data_structures/artifacts.py
mlxp/data_structures/config_dict.py
mlxp/data_structures/dataframe.py
mlxp/data_structures/schemas.py
mlxp/data_structures/contrib/__init__.py
mlxp/data_structures/contrib/artifacts.py
tutorial/__init__.py
tutorial/core_app.py
tutorial/main.py
tutorial/read.py
MLXP-1.0.4.dist-info/LICENSE
MLXP-1.0.4.dist-info/METADATA
MLXP-1.0.4.dist-info/WHEEL
MLXP-1.0.4.dist-info/entry_points.txt
MLXP-1.0.4.dist-info/top_level.txt
MLXP-1.0.4.dist-info/RECORD
