Metadata-Version: 2.1
Name: MLXP
Version: 1.0.4
Summary: A framework for conducting machine learning experiments in python
Home-page: https://github.com/inria-thoth/mlxp
Author: Michael Arbel
Author-email: michael.n.arbel@gmail.com
License: MIT License
Classifier: Programming Language :: Python :: 3.8
Requires-Python: >=3.8
License-File: LICENSE
Requires-Dist: hydra-core>=1.3.2
Requires-Dist: omegaconf>=2.2.3
Requires-Dist: dill>=0.3.6
Requires-Dist: GitPython>=3.1.31
Requires-Dist: pandas>=1.3.4
Requires-Dist: ply>=3.11
Requires-Dist: PyYAML>=6.0
Requires-Dist: tinydb>=4.7.1
